gradio_testaudio/__init__.py
gradio_testaudio/testaudio.py
gradio_testaudio/testaudio.pyi
gradio_testaudio/templates/component/__vite-browser-external-2447137e.js
gradio_testaudio/templates/component/index-822bf93c.js
gradio_testaudio/templates/component/index.js
gradio_testaudio/templates/component/module-2c3384e6.js
gradio_testaudio/templates/component/module-ebee7a2c.js
gradio_testaudio/templates/component/module-ef7e7a9a.js
gradio_testaudio/templates/component/style.css
gradio_testaudio/templates/component/wrapper-98f94c21-f7f71f53.js
gradio_testaudio/templates/example/index.js
gradio_testaudio/templates/example/style.css
gradio_testaudio-0.0.1.dist-info/METADATA
gradio_testaudio-0.0.1.dist-info/WHEEL
gradio_testaudio-0.0.1.dist-info/RECORD
